roadguard/__init__.py
roadguard/constant.py
roadguard/function.py
roadguard/analyze/__init__.py
roadguard/core/__init__.py
roadguard/core/rwlock.py
roadguard/core/struct.py
roadguard/feed/__init__.py
roadguard/feed/camera.py
roadguard/feed/file.py
roadguard/feed/parameter.py
roadguard/feed/speaker.py
roadguard/feed/mock/__init__.py
roadguard/ingest/__init__.py
roadguard/ingest/audio/__init__.py
roadguard/ingest/audio/function.py
roadguard/ingest/audio/parameter.py
roadguard/ingest/audio/prompt.py
roadguard/ingest/video/__init__.py
roadguard/ingest/video/function.py
roadguard/ingest/video/parameter.py
roadguard/ingest/video/prompt.py
serve/__init__.py
Libe-0.0.0.dist-info/LICENSE
Libe-0.0.0.dist-info/METADATA
Libe-0.0.0.dist-info/WHEEL
Libe-0.0.0.dist-info/top_level.txt
Libe-0.0.0.dist-info/RECORD
